{
  "$schema": "../gen/schemas/desktop-schema.json",
  "identifier": "default",
  "description": "Capability for the main window",
  "windows": [
    "main"
  ],
  "permissions": [
    "core:default",
    "opener:default",
    "core:window:allow-minimize",
    "core:window:allow-maximize",
    "core:window:allow-close",
    "core:window:allow-set-always-on-top",
    "core:window:allow-toggle-maximize",
    "core:window:allow-is-maximized",
    "core:window:allow-is-always-on-top",
    "core:window:allow-set-size",
    "core:window:allow-set-position",
    "core:window:allow-start-dragging",
    "core:webview:default",
    "core:webview:allow-create-webview-window",
    "core:webview:allow-webview-close",
    "core:webview:allow-webview-position",
    "core:webview:allow-webview-size",
    "core:window:allow-create",
    "core:window:allow-center",
    "core:window:allow-show",
    "core:window:allow-hide",
    "core:window:allow-set-focus",
    "fs:default",
    "fs:read-all",
    "fs:write-all",
    "fs:allow-rename",
    "fs:allow-mkdir",
    "fs:allow-exists",
    "fs:allow-watch",
    "fs:read-dirs",
    {
      "identifier": "fs:scope",
      "allow": [
        "**/*"
      ]
    }
  ]
}